string2string/__init__.py
string2string/alignment/__init__.py
string2string/alignment/classical.py
string2string/distance/__init__.py
string2string/distance/classical.py
string2string/metrics/__init__.py
string2string/metrics/exact_match.py
string2string/metrics/rouge.py
string2string/metrics/sbleu.py
string2string/misc/__init__.py
string2string/misc/basic_functions.py
string2string/misc/default_tokenizer.py
string2string/misc/hash_functions.py
string2string/misc/model_embeddings.py
string2string/misc/plotting_functions.py
string2string/misc/word_embeddings.py
string2string/search/__init__.py
string2string/search/classical.py
string2string/search/faiss_search.py
string2string/similarity/__init__.py
string2string/similarity/bartscore.py
string2string/similarity/bertscore.py
string2string/similarity/classical.py
string2string/similarity/cosine_similarity.py
string2string-0.0.152.dist-info/licenses/LICENSE
string2string-0.0.152.dist-info/METADATA
string2string-0.0.152.dist-info/WHEEL
string2string-0.0.152.dist-info/top_level.txt
string2string-0.0.152.dist-info/RECORD
