Metadata-Version: 2.4
Name: string2string
Version: 0.0.152
Summary: String-to-String Algorithms for Natural Language Processing
Home-page: https://github.com/stanfordnlp/string2string
Author: Mirac Suzgun
Author-email: Mirac Suzgun <msuzgun@cs.stanford.edu>
License: MIT
Project-URL: Homepage, https://github.com/stanfordnlp/string2string
Project-URL: Documentation, https://string2string.readthedocs.io/
Project-URL: Repository, https://github.com/stanfordnlp/string2string
Project-URL: Issues, https://github.com/stanfordnlp/string2string/issues
Keywords: string matching,pattern matching,edit distance,string to string correction,string to string matching,Levenshtein edit distance,Hamming distance,Damerau-Levenshtein distance,Jaro-Winkler distance,longest common subsequence,longest common substring,dynamic programming,approximate string matching,semantic similarity,natural language processing,NLP,information retrieval,rouge,sacrebleu,bertscore,bartscore,fasttext,glove,cosine similarity,Smith-Waterman,Needleman-Wunsch,Hirschberg,Karp-Rabi
Classifier: Programming Language :: Python :: 3
Classifier: Programming Language :: Python :: 3.10
Classifier: Programming Language :: Python :: 3.11
Classifier: Programming Language :: Python :: 3.12
Classifier: License :: OSI Approved :: MIT License
Classifier: Operating System :: OS Independent
Classifier: Typing :: Typed
Classifier: Intended Audience :: Developers
Classifier: Intended Audience :: Science/Research
Classifier: Topic :: Scientific/Engineering :: Artificial Intelligence
Classifier: Topic :: Text Processing :: Linguistic
Requires-Python: >=3.10
License-File: LICENSE
Requires-Dist: torch
Requires-Dist: numpy
Requires-Dist: transformers
Requires-Dist: datasets
Requires-Dist: faiss-cpu
Requires-Dist: bert_score
Requires-Dist: fasttext
Requires-Dist: pandas
Requires-Dist: joblib
Requires-Dist: sacrebleu
Requires-Dist: rouge-score
Requires-Dist: networkx
Provides-Extra: dev
Requires-Dist: pytest>=7.0; extra == "dev"
Requires-Dist: pytest-cov>=4.0; extra == "dev"
Dynamic: author
Dynamic: home-page
Dynamic: license-file
Dynamic: requires-python
